{
    "season": "2021/2022",
    "teams": [
        961,
        802,
        1225,
        1222,
        1226,
        805,
        787,
        785,
        1223,
        112,
        799,
        1224,
        1149,
        771,
        1220,
        788,
        1219,
        796
    ],
    "top_3_elos": {
        "961": 1653.071435411171,
        "802": 1644.989361861887,
        "1225": 1616.6328621039195
    },
    "bottom_3_elos": {
        "788": 1400.615978182132,
        "1219": 1397.878587414668,
        "796": 1368.9067439233522
    }
}