{
    "season": "2014/2015",
    "teams": [
        187,
        105,
        109,
        196,
        191,
        185,
        203,
        194,
        199,
        188,
        201,
        200,
        197,
        192,
        202,
        198,
        205,
        204
    ],
    "top_3_elos": {
        "187": 1640.251275632633,
        "105": 1630.2375358047343,
        "109": 1591.374862325396
    },
    "bottom_3_elos": {
        "198": 1405.2526375953337,
        "205": 1413.2316825974153,
        "204": 1409.6253211840738
    }
}